partner_availability/__init__.py
partner_availability/models.py
partner_availability/service.py
partner_availability_config-0.1.1.dist-info/METADATA
partner_availability_config-0.1.1.dist-info/WHEEL
partner_availability_config-0.1.1.dist-info/top_level.txt
partner_availability_config-0.1.1.dist-info/RECORD
