Metadata-Version: 2.4
Name: partner-availability-config
Version: 0.1.1
Summary: Simple package for managing partner availability configurations across tenants
Author: Arturk Mammadli
Author-email: Arturk Mammadli <amemmedli@cuddlynest.com>
License: MIT
Keywords: partner,availability,configuration,tenant
Classifier: Development Status :: 4 - Beta
Classifier: Intended Audience :: Developers
Classifier: Programming Language :: Python :: 3
Classifier: Programming Language :: Python :: 3.8
Classifier: Programming Language :: Python :: 3.9
Classifier: Programming Language :: Python :: 3.10
Classifier: Programming Language :: Python :: 3.11
Requires-Python: >=3.8
Requires-Dist: sqlalchemy<2.0.0,>=1.4.0
Provides-Extra: dev
Requires-Dist: pytest>=7.0.0; extra == "dev"
Requires-Dist: black>=23.0.0; extra == "dev"
Dynamic: author
Dynamic: requires-python
